strings.cpython-37m-darwin.so
strings_pkg/__init__.py
strings_pkg-0.0.1.dist-info/LICENSE
strings_pkg-0.0.1.dist-info/METADATA
strings_pkg-0.0.1.dist-info/WHEEL
strings_pkg-0.0.1.dist-info/top_level.txt
strings_pkg-0.0.1.dist-info/RECORD
